<annotation>
    <folder>images</folder>
    <filename>61BWZ0bMLTL-_SL1500_.jpg</filename>
    <size>
        <width>1500</width>
        <height>1481</height>
        <depth>3</depth>
    </size>
    <object>
        <name>PlasticBottle</name>
        <pose>Unspecified</pose>
        <truncated>0</truncated>
        <difficult>0</difficult>
        <bndbox>
            <xmin>466.689362</xmin>
            <ymin>17.988470</ymin>
            <xmax>1018.321289</xmax>
            <ymax>1463.012207</ymax>
        </bndbox>
    </object>
</annotation>
