<annotation>
    <folder>images</folder>
    <filename>71GLwgy4pLL-_AC_SX466_.jpg</filename>
    <size>
        <width>466</width>
        <height>428</height>
        <depth>3</depth>
    </size>
    <object>
        <name>PlasticCap</name>
        <pose>Unspecified</pose>
        <truncated>0</truncated>
        <difficult>0</difficult>
        <bndbox>
            <xmin>40.914162</xmin>
            <ymin>300.299072</ymin>
            <xmax>112.759659</xmax>
            <ymax>364.149536</ymax>
        </bndbox>
    </object>
    <object>
        <name>PlasticCap</name>
        <pose>Unspecified</pose>
        <truncated>0</truncated>
        <difficult>0</difficult>
        <bndbox>
            <xmin>118.746780</xmin>
            <ymin>53.876156</ymin>
            <xmax>183.607300</xmax>
            <ymax>86.799072</ymax>
        </bndbox>
    </object>
    <object>
        <name>PlasticCap</name>
        <pose>Unspecified</pose>
        <truncated>0</truncated>
        <difficult>0</difficult>
        <bndbox>
            <xmin>11.976396</xmin>
            <ymin>109.745323</ymin>
            <xmax>56.879826</xmax>
            <ymax>158.630829</ymax>
        </bndbox>
    </object>
    <object>
        <name>PlasticCap</name>
        <pose>Unspecified</pose>
        <truncated>0</truncated>
        <difficult>0</difficult>
        <bndbox>
            <xmin>5.989270</xmin>
            <ymin>178.584106</ymin>
            <xmax>41.912018</xmax>
            <ymax>242.434586</ymax>
        </bndbox>
    </object>
    <object>
        <name>PlasticCap</name>
        <pose>Unspecified</pose>
        <truncated>0</truncated>
        <difficult>0</difficult>
        <bndbox>
            <xmin>140.699570</xmin>
            <ymin>161.623840</ymin>
            <xmax>210.549347</xmax>
            <ymax>216.495316</ymax>
        </bndbox>
    </object>
    <object>
        <name>PlasticCap</name>
        <pose>Unspecified</pose>
        <truncated>0</truncated>
        <difficult>0</difficult>
        <bndbox>
            <xmin>53.886265</xmin>
            <ymin>152.644867</ymin>
            <xmax>125.731750</xmax>
            <ymax>210.509354</ymax>
        </bndbox>
    </object>
    <object>
        <name>PlasticCap</name>
        <pose>Unspecified</pose>
        <truncated>0</truncated>
        <difficult>0</difficult>
        <bndbox>
            <xmin>208.553650</xmin>
            <ymin>106.752342</ymin>
            <xmax>252.459229</xmax>
            <ymax>171.600479</ymax>
        </bndbox>
    </object>
    <object>
        <name>PlasticCap</name>
        <pose>Unspecified</pose>
        <truncated>0</truncated>
        <difficult>0</difficult>
        <bndbox>
            <xmin>105.774681</xmin>
            <ymin>85.801407</ymin>
            <xmax>161.654510</xmax>
            <ymax>152.644867</ymax>
        </bndbox>
    </object>
    <object>
        <name>PlasticCap</name>
        <pose>Unspecified</pose>
        <truncated>0</truncated>
        <difficult>0</difficult>
        <bndbox>
            <xmin>346.257507</xmin>
            <ymin>72.831764</ymin>
            <xmax>415.109436</xmax>
            <ymax>139.675232</ymax>
        </bndbox>
    </object>
    <object>
        <name>PlasticCap</name>
        <pose>Unspecified</pose>
        <truncated>0</truncated>
        <difficult>0</difficult>
        <bndbox>
            <xmin>264.433472</xmin>
            <ymin>99.768684</ymin>
            <xmax>336.278961</xmax>
            <ymax>176.588776</ymax>
        </bndbox>
    </object>
    <object>
        <name>PlasticCap</name>
        <pose>Unspecified</pose>
        <truncated>0</truncated>
        <difficult>0</difficult>
        <bndbox>
            <xmin>182.609451</xmin>
            <ymin>225.474289</ymin>
            <xmax>253.457092</xmax>
            <ymax>291.320099</ymax>
        </bndbox>
    </object>
    <object>
        <name>PlasticCap</name>
        <pose>Unspecified</pose>
        <truncated>0</truncated>
        <difficult>0</difficult>
        <bndbox>
            <xmin>98.789703</xmin>
            <ymin>199.535034</ymin>
            <xmax>171.633041</xmax>
            <ymax>272.364502</ymax>
        </bndbox>
    </object>
    <object>
        <name>PlasticCap</name>
        <pose>Unspecified</pose>
        <truncated>0</truncated>
        <difficult>0</difficult>
        <bndbox>
            <xmin>25.946352</xmin>
            <ymin>234.453262</ymin>
            <xmax>84.819740</xmax>
            <ymax>302.294373</ymax>
        </bndbox>
    </object>
    <object>
        <name>PlasticCap</name>
        <pose>Unspecified</pose>
        <truncated>0</truncated>
        <difficult>0</difficult>
        <bndbox>
            <xmin>193.585831</xmin>
            <ymin>323.245331</ymin>
            <xmax>264.433472</xmax>
            <ymax>382.107483</ymax>
        </bndbox>
    </object>
    <object>
        <name>PlasticCap</name>
        <pose>Unspecified</pose>
        <truncated>0</truncated>
        <difficult>0</difficult>
        <bndbox>
            <xmin>366.214600</xmin>
            <ymin>224.476639</ymin>
            <xmax>434.068665</xmax>
            <ymax>294.313080</ymax>
        </bndbox>
    </object>
    <object>
        <name>PlasticCap</name>
        <pose>Unspecified</pose>
        <truncated>0</truncated>
        <difficult>0</difficult>
        <bndbox>
            <xmin>288.381989</xmin>
            <ymin>287.329437</ymin>
            <xmax>359.229614</xmax>
            <ymax>362.154205</ymax>
        </bndbox>
    </object>
</annotation>
