<annotation>
    <folder>train</folder>
    <filename>image (5) 2.jpeg</filename>
    <size>
        <width>192</width>
        <height>263</height>
        <depth>3</depth>
    </size>
    <object>
        <name>PlasticBag</name>
        <pose>Unspecified</pose>
        <truncated>0</truncated>
        <difficult>0</difficult>
        <bndbox>
            <xmin>15.921875</xmin>
            <ymin>18.931572</ymin>
            <xmax>177.078125</xmax>
            <ymax>252.041840</ymax>
        </bndbox>
    </object>
</annotation>
