<annotation>
    <folder>images</folder>
    <filename>fresh-water-bottle-mockup_358694-279.jpg</filename>
    <size>
        <width>626</width>
        <height>418</height>
        <depth>3</depth>
    </size>
    <object>
        <name>PlasticBottle</name>
        <pose>Unspecified</pose>
        <truncated>0</truncated>
        <difficult>0</difficult>
        <bndbox>
            <xmin>249.602234</xmin>
            <ymin>32.923443</ymin>
            <xmax>363.420105</xmax>
            <ymax>400.043060</ymax>
        </bndbox>
    </object>
</annotation>
