<annotation>
    <folder>train</folder>
    <filename>step1-journey-of-bottle.png</filename>
    <size>
        <width>540</width>
        <height>849</height>
        <depth>3</depth>
    </size>
    <object>
        <name>PlasticBottle</name>
        <pose>Unspecified</pose>
        <truncated>0</truncated>
        <difficult>0</difficult>
        <bndbox>
            <xmin>131.757401</xmin>
            <ymin>3.996463</ymin>
            <xmax>403.253723</xmax>
            <ymax>785.075378</ymax>
        </bndbox>
    </object>
</annotation>
