<annotation>
	<folder>train</folder>
	<filename>image6.jpg</filename>
	<path>/Users/alex.steiner/Desktop/Service in Actions/TrashSortingRobot/train/image6.jpg</path>
	<source>
		<database>Unknown</database>
	</source>
	<size>
		<width>2305</width>
		<height>3072</height>
		<depth>3</depth>
	</size>
	<segmented>0</segmented>
	<object>
		<name>plasticBottle</name>
		<pose>Unspecified</pose>
		<truncated>0</truncated>
		<difficult>0</difficult>
		<bndbox>
			<xmin>417</xmin>
			<ymin>277</ymin>
			<xmax>1249</xmax>
			<ymax>2559</ymax>
		</bndbox>
	</object>
</annotation>
